banana_dev/__init__.py
banana_dev/api.py
banana_dev/client.py
banana_dev/config.py
banana_dev/generics.py
banana_dev/package.py
banana_dev-6.3.0.dist-info/METADATA
banana_dev-6.3.0.dist-info/WHEEL
banana_dev-6.3.0.dist-info/top_level.txt
banana_dev-6.3.0.dist-info/RECORD
