Metadata-Version: 2.1
Name: banana-dev
Version: 6.3.0
Summary: The banana package is a python client to interact with your machine learning models hosted on Banana
Home-page: https://www.banana.dev
Author: Erik Dunteman
Author-email: erik@banana.dev
License: MIT
Keywords: Banana client,API wrapper,Banana,SDK
Classifier: Development Status :: 4 - Beta
Classifier: Intended Audience :: Developers
Classifier: Topic :: Software Development :: Build Tools
Classifier: License :: OSI Approved :: MIT License
Classifier: Programming Language :: Python :: 3.7
Classifier: Programming Language :: Python :: 3.8
Requires-Dist: requests <3.0.0,>=2.26.0
